dev/__init__.py
dev/dev_client.py
orcatech_client/__init__.py
orcatech_client/client.py
orcatech_client/config.py
orcatech_client/exceptions.py
orcatech_client/http_client.py
orcatech_client/schema_types.py
orcatech_client/schemas.py
orcatech_client/utils.py
orcatech_python_api_client/__init__.py
orcatech_python_api_client/client.py
orcatech_python_api_client/config.py
orcatech_python_api_client/exceptions.py
orcatech_python_api_client/http_client.py
orcatech_python_api_client/schema_types.py
orcatech_python_api_client/schema_types_old.py
orcatech_python_api_client/schemas.py
orcatech_python_api_client/utils.py
orcatech_python_api_client/aws/__init__.py
orcatech_python_api_client/aws/aws_cert_manager.py
orcatech_python_api_client/aws/example_aws_credentials.py
orcatech_client-0.1.20.dist-info/METADATA
orcatech_client-0.1.20.dist-info/WHEEL
orcatech_client-0.1.20.dist-info/entry_points.txt
orcatech_client-0.1.20.dist-info/top_level.txt
orcatech_client-0.1.20.dist-info/RECORD
